odoo/addons/ssi_rma_account/README.rst
odoo/addons/ssi_rma_account/__init__.py
odoo/addons/ssi_rma_account/__manifest__.py
odoo/addons/ssi_rma_account/data/rma_policy_data.xml
odoo/addons/ssi_rma_account/data/rma_policy_field_data.xml
odoo/addons/ssi_rma_account/i18n/ssi_rma_account.pot
odoo/addons/ssi_rma_account/models/__init__.py
odoo/addons/ssi_rma_account/models/rma_customer_line.py
odoo/addons/ssi_rma_account/models/rma_line_mixin.py
odoo/addons/ssi_rma_account/models/rma_mixin.py
odoo/addons/ssi_rma_account/models/rma_operation.py
odoo/addons/ssi_rma_account/models/rma_policy.py
odoo/addons/ssi_rma_account/models/rma_supplier.py
odoo/addons/ssi_rma_account/models/rma_supplier_line.py
odoo/addons/ssi_rma_account/security/ir.model.access.csv
odoo/addons/ssi_rma_account/static/description/icon.png
odoo/addons/ssi_rma_account/views/rma_customer_views.xml
odoo/addons/ssi_rma_account/views/rma_operation_views.xml
odoo/addons/ssi_rma_account/views/rma_supplier_views.xml
odoo/addons/ssi_rma_account/wizards/__init__.py
odoo/addons/ssi_rma_account/wizards/link_journal_item_rma_line.py
odoo/addons/ssi_rma_account/wizards/link_journal_item_rma_line_views.xml
odoo14_addon_ssi_rma_account-14.0.1.7.0.dist-info/METADATA
odoo14_addon_ssi_rma_account-14.0.1.7.0.dist-info/WHEEL
odoo14_addon_ssi_rma_account-14.0.1.7.0.dist-info/top_level.txt
odoo14_addon_ssi_rma_account-14.0.1.7.0.dist-info/RECORD
